{
  "name": "VerwaltungPro – Ausbildungsverwaltung",
  "short_name": "VerwaltungPro",
  "description": "Digitale Verwaltung für Bildungszentren – Kurse, Teilnehmer, Fortschritt",
  "start_url": "./HBZVerwaltung.html",
  "scope": "./",
  "display": "standalone",
  "background_color": "#f0f2f8",
  "theme_color": "#1e2230",
  "orientation": "any",
  "categories": ["education", "business"],
  "lang": "de",
  "icons": [
    { "src": "icon-vp-192.png", "sizes": "192x192", "type": "image/png", "purpose": "any maskable" },
    { "src": "icon-vp-512.png", "sizes": "512x512", "type": "image/png", "purpose": "any maskable" }
  ]
}
